[
  {"id": "bim-kadikoy-1", "name": "BİM Kadıköy", "chain": "BİM", "lat": 40.9902, "lng": 29.0298},
  {"id": "a101-kadikoy-1", "name": "A101 Kadıköy", "chain": "A101", "lat": 40.9885, "lng": 29.0271},
  {"id": "migros-kadikoy-1", "name": "Migros Kadıköy", "chain": "Migros", "lat": 40.9921, "lng": 29.0245},
  {"id": "sok-kadikoy-1", "name": "Şok Kadıköy", "chain": "Şok", "lat": 40.9867, "lng": 29.0312},
  {"id": "carrefour-kadikoy-1", "name": "CarrefourSA Kadıköy", "chain": "CarrefourSA", "lat": 40.9943, "lng": 29.0338},
  {"id": "bim-besiktas-1", "name": "BİM Beşiktaş", "chain": "BİM", "lat": 41.0422, "lng": 29.0089},
  {"id": "migros-besiktas-1", "name": "Migros Beşiktaş", "chain": "Migros", "lat": 41.0456, "lng": 29.0045},
  {"id": "a101-besiktas-1", "name": "A101 Beşiktaş", "chain": "A101", "lat": 41.0398, "lng": 29.0112},
  {"id": "bim-uskudar-1", "name": "BİM Üsküdar", "chain": "BİM", "lat": 41.0224, "lng": 29.0156},
  {"id": "migros-uskudar-1", "name": "Migros Üsküdar", "chain": "Migros", "lat": 41.0256, "lng": 29.0189},
  {"id": "bim-sisli-1", "name": "BİM Şişli", "chain": "BİM", "lat": 41.0602, "lng": 28.9876},
  {"id": "migros-sisli-1", "name": "Migros Şişli", "chain": "Migros", "lat": 41.0634, "lng": 28.9845},
  {"id": "a101-sisli-1", "name": "A101 Şişli", "chain": "A101", "lat": 41.0578, "lng": 28.9912},
  {"id": "bim-bakirkoy-1", "name": "BİM Bakırköy", "chain": "BİM", "lat": 40.9789, "lng": 28.8723},
  {"id": "migros-bakirkoy-1", "name": "Migros Bakırköy", "chain": "Migros", "lat": 40.9812, "lng": 28.8756},
  {"id": "bim-ankara-kizilay", "name": "BİM Kızılay", "chain": "BİM", "lat": 39.9208, "lng": 32.8541},
  {"id": "migros-ankara-kizilay", "name": "Migros Kızılay", "chain": "Migros", "lat": 39.9234, "lng": 32.8567},
  {"id": "a101-ankara-kizilay", "name": "A101 Kızılay", "chain": "A101", "lat": 39.9189, "lng": 32.8512},
  {"id": "bim-ankara-cankaya", "name": "BİM Çankaya", "chain": "BİM", "lat": 39.9089, "lng": 32.8612},
  {"id": "migros-izmir-konak", "name": "Migros Konak", "chain": "Migros", "lat": 38.4189, "lng": 27.1287},
  {"id": "bim-izmir-konak", "name": "BİM Konak", "chain": "BİM", "lat": 38.4167, "lng": 27.1312},
  {"id": "a101-izmir-konak", "name": "A101 Konak", "chain": "A101", "lat": 38.4212, "lng": 27.1256},
  {"id": "bim-izmir-karsiyaka", "name": "BİM Karşıyaka", "chain": "BİM", "lat": 38.4612, "lng": 27.1189},
  {"id": "migros-izmir-karsiyaka", "name": "Migros Karşıyaka", "chain": "Migros", "lat": 38.4634, "lng": 27.1212}
]
